django_contactme/__init__.py
django_contactme/admin.py
django_contactme/apps.py
django_contactme/compat.py
django_contactme/forms.py
django_contactme/models.py
django_contactme/signals.py
django_contactme/signed.py
django_contactme/urls.py
django_contactme/utils.py
django_contactme/views.py
django_contactme/conf/__init__.py
django_contactme/conf/defaults.py
django_contactme/migrations/0001_initial.py
django_contactme/migrations/0002_auto_20150819_1356.py
django_contactme/migrations/__init__.py
django_contactme/templates/404.html
django_contactme/templates/django_contactme/400-debug.html
django_contactme/templates/django_contactme/accepted.html
django_contactme/templates/django_contactme/base.html
django_contactme/templates/django_contactme/confirmation_email.html
django_contactme/templates/django_contactme/confirmation_email.txt
django_contactme/templates/django_contactme/confirmation_sent.html
django_contactme/templates/django_contactme/confirmation_sent_ajax.html
django_contactme/templates/django_contactme/contact_received_email.txt
django_contactme/templates/django_contactme/contactme.html
django_contactme/templates/django_contactme/discarded.html
django_contactme/templates/django_contactme/discarded_ajax.html
django_contactme/templates/django_contactme/field_errors.html
django_contactme/templates/django_contactme/form.html
django_contactme/templates/django_contactme/preview.html
django_contactme/templates/django_contactme/preview_ajax.html
django_contactme/templatetags/__init__.py
django_contactme/templatetags/contactme.py
django_contactme/tests/__init__.py
django_contactme/tests/apps.py
django_contactme/tests/settings.py
django_contactme/tests/test_forms.py
django_contactme/tests/test_jqueryplugin.py
django_contactme/tests/test_views.py
django_contactme/tests/urls.py
django_contactme/tests/views.py
django_contactme-1.3.0.dist-info/DESCRIPTION.rst
django_contactme-1.3.0.dist-info/METADATA
django_contactme-1.3.0.dist-info/metadata.json
django_contactme-1.3.0.dist-info/RECORD
django_contactme-1.3.0.dist-info/top_level.txt
django_contactme-1.3.0.dist-info/WHEEL
